ZhihuZhoukanBianchengXiaobaixuePythonZongdi103Qi/README.md
ZhihuZhoukanBianchengXiaobaixuePythonZongdi103Qi/__init__.py
ZhihuZhoukanBianchengXiaobaixuePythonZongdi103Qi/__main__.py
ZhihuZhoukanBianchengXiaobaixuePythonZongdi103Qi/file.epub
ZhihuZhoukanBianchengXiaobaixuePythonZongdi103Qi/index.html
ZhihuZhoukanBianchengXiaobaixuePythonZongdi103Qi/css/__init__.py
ZhihuZhoukanBianchengXiaobaixuePythonZongdi103Qi/css/annotations.css
ZhihuZhoukanBianchengXiaobaixuePythonZongdi103Qi/css/main.css
ZhihuZhoukanBianchengXiaobaixuePythonZongdi103Qi/css/normalize.css
ZhihuZhoukanBianchengXiaobaixuePythonZongdi103Qi/css/popup.css
ZhihuZhoukanBianchengXiaobaixuePythonZongdi103Qi/font/__init__.py
ZhihuZhoukanBianchengXiaobaixuePythonZongdi103Qi/font/fontello.eot
ZhihuZhoukanBianchengXiaobaixuePythonZongdi103Qi/font/fontello.svg
ZhihuZhoukanBianchengXiaobaixuePythonZongdi103Qi/font/fontello.ttf
ZhihuZhoukanBianchengXiaobaixuePythonZongdi103Qi/font/fontello.woff
ZhihuZhoukanBianchengXiaobaixuePythonZongdi103Qi/img/__init__.py
ZhihuZhoukanBianchengXiaobaixuePythonZongdi103Qi/img/annotator-glyph-sprite.png
ZhihuZhoukanBianchengXiaobaixuePythonZongdi103Qi/img/annotator-icon-sprite.png
ZhihuZhoukanBianchengXiaobaixuePythonZongdi103Qi/img/apple-touch-icon.png
ZhihuZhoukanBianchengXiaobaixuePythonZongdi103Qi/img/cancelfullscreen.png
ZhihuZhoukanBianchengXiaobaixuePythonZongdi103Qi/img/close.png
ZhihuZhoukanBianchengXiaobaixuePythonZongdi103Qi/img/fullscreen.png
ZhihuZhoukanBianchengXiaobaixuePythonZongdi103Qi/img/loader.gif
ZhihuZhoukanBianchengXiaobaixuePythonZongdi103Qi/img/menu-icon.png
ZhihuZhoukanBianchengXiaobaixuePythonZongdi103Qi/img/save.png
ZhihuZhoukanBianchengXiaobaixuePythonZongdi103Qi/img/saved.png
ZhihuZhoukanBianchengXiaobaixuePythonZongdi103Qi/img/settings-s.png
ZhihuZhoukanBianchengXiaobaixuePythonZongdi103Qi/img/settings.png
ZhihuZhoukanBianchengXiaobaixuePythonZongdi103Qi/img/star.png
ZhihuZhoukanBianchengXiaobaixuePythonZongdi103Qi/js/__init__.py
zhihu_zhoukan_biancheng_xiaobaixue_python_zongdi_103_qi-2024.3.2.0.dist-info/METADATA
zhihu_zhoukan_biancheng_xiaobaixue_python_zongdi_103_qi-2024.3.2.0.dist-info/WHEEL
zhihu_zhoukan_biancheng_xiaobaixue_python_zongdi_103_qi-2024.3.2.0.dist-info/entry_points.txt
zhihu_zhoukan_biancheng_xiaobaixue_python_zongdi_103_qi-2024.3.2.0.dist-info/top_level.txt
zhihu_zhoukan_biancheng_xiaobaixue_python_zongdi_103_qi-2024.3.2.0.dist-info/RECORD
